tatara/__init__.py
tatara/client_state.py
tatara/dataset.py
tatara/evals/__init__.py
tatara/evals/eval.py
tatara/evals/eval_types.py
tatara/evals/id_generator.py
tatara/evals/model_package.py
tatara/evals/record.py
tatara/evals/recorder.py
tatara/evals/tatara_recorder.py
tatara/network/__init__.py
tatara/network/_tatara_network_client.py
tatara/network/endpoints.py
tatara/tatara.py
tatara/tatara_logging/__init__.py
tatara/tatara_logging/_background_queue_logger.py
tatara/tatara_logging/_record_keys.py
tatara/tatara_logging/empty_span.py
tatara/tatara_logging/empty_trace.py
tatara/tatara_logging/rating.py
tatara/tatara_logging/span.py
tatara/tatara_logging/trace.py
tatara/tatara_logging/utils.py
tatara/tatara_types.py
tatara/tests/__init__.py
tatara/tests/conftest.py
tatara/tests/test_background_queue_logger.py
tatara/tests/test_log_decorators.py
tatara-0.2.4.dist-info/LICENSE
tatara-0.2.4.dist-info/METADATA
tatara-0.2.4.dist-info/WHEEL
tatara-0.2.4.dist-info/RECORD
