Metadata-Version: 2.1
Name: tatara
Version: 0.2.4
Summary: 
Author: Tatara
Author-email: support@tatara.ai
Requires-Python: >=3.8
Classifier: Programming Language :: Python :: 3
Classifier: Programming Language :: Python :: 3.8
Classifier: Programming Language :: Python :: 3.9
Classifier: Programming Language :: Python :: 3.10
Classifier: Programming Language :: Python :: 3.11
Requires-Dist: requests (>=2.31.0,<3.0.0)
Requires-Dist: wrapt (>=1.16.0,<2.0.0)
